vistock/__init__.py
vistock/core/__init__.py
vistock/core/constants.py
vistock/core/enums.py
vistock/core/exceptions.py
vistock/core/models.py
vistock/core/utils.py
vistock/core/interfaces/__init__.py
vistock/core/interfaces/ivistockfetcher.py
vistock/core/interfaces/ivistockparser.py
vistock/core/interfaces/ivistocksearch.py
vistock/modules/__init__.py
vistock/modules/_24hmoney/__init__.py
vistock/modules/_24hmoney/fetchers.py
vistock/modules/_24hmoney/parsers.py
vistock/modules/_24hmoney/search.py
vistock/modules/dnse/__init__.py
vistock/modules/dnse/fetchers.py
vistock/modules/dnse/parsers.py
vistock/modules/dnse/search.py
vistock/modules/simplize/__init__.py
vistock/modules/simplize/fetchers.py
vistock/modules/simplize/parsers.py
vistock/modules/simplize/search.py
vistock/modules/ssc/__init__.py
vistock/modules/vietstock/__init__.py
vistock/modules/vietstock/fetchers.py
vistock/modules/vietstock/parsers.py
vistock/modules/vietstock/search.py
vistock/modules/vndirect/__init__.py
vistock/modules/vndirect/fetchers.py
vistock/modules/vndirect/parsers.py
vistock/modules/vndirect/search.py
vistock-0.1.0b6.dist-info/licenses/LICENSE
vistock-0.1.0b6.dist-info/METADATA
vistock-0.1.0b6.dist-info/WHEEL
vistock-0.1.0b6.dist-info/top_level.txt
vistock-0.1.0b6.dist-info/RECORD
