Metadata-Version: 2.4
Name: vistock
Version: 0.1.0b6
Summary: Vistock is an open-source library focused on searching, retrieving, and analyzing Vietnamese stock market data.
Home-page: https://github.com/kaiismith/vistock
Author: Thang Duong
Author-email: kaiismith.business@gmail.com
License: Apache-2.0
Project-URL: Bug Reports, https://github.com/kaiismith/vistock/issues
Project-URL: Source, https://github.com/kaiismith/vistock
Project-URL: Documentation, https://github.com/kaiismith/vistock#readme
Keywords: stock,vietnamese,vietnam,financial data,stock market
Classifier: Development Status :: 3 - Alpha
Classifier: Intended Audience :: Developers
Classifier: License :: OSI Approved :: Apache Software License
Classifier: Programming Language :: Python :: 3.12
Classifier: Programming Language :: Python :: 3.13
Classifier: Programming Language :: Python :: 3.14
Classifier: Programming Language :: Python :: 3.15
Classifier: Topic :: Software Development :: Libraries
Classifier: Topic :: Office/Business :: Financial
Requires-Python: >=3.12
License-File: LICENSE
Requires-Dist: annotated-types==0.7.0
Requires-Dist: anyio==4.9.0
Requires-Dist: build==1.2.2.post1
Requires-Dist: certifi==2025.7.14
Requires-Dist: charset-normalizer==3.4.2
Requires-Dist: click==8.2.1
Requires-Dist: colorama==0.4.6
Requires-Dist: exceptiongroup==1.3.0
Requires-Dist: h11==0.16.0
Requires-Dist: httpcore==1.0.9
Requires-Dist: httpx==0.28.1
Requires-Dist: idna==3.10
Requires-Dist: numpy==2.3.1
Requires-Dist: packaging==25.0
Requires-Dist: pandas==2.3.1
Requires-Dist: pip-tools==7.4.1
Requires-Dist: pydantic==2.11.7
Requires-Dist: pydantic-core==2.33.2
Requires-Dist: pyproject-hooks==1.2.0
Requires-Dist: python-dateutil==2.9.0.post0
Requires-Dist: pytz==2025.2
Requires-Dist: requests==2.32.4
Requires-Dist: six==1.17.0
Requires-Dist: sniffio==1.3.1
Requires-Dist: tenacity==9.1.2
Requires-Dist: tomli==2.2.1
Requires-Dist: typing-extensions==4.14.1
Requires-Dist: typing-inspection==0.4.1
Requires-Dist: tzdata==2025.2
Requires-Dist: tzlocal==5.3.1
Requires-Dist: urllib3==2.5.0
Requires-Dist: wheel==0.45.1
Dynamic: author
Dynamic: author-email
Dynamic: classifier
Dynamic: description
Dynamic: description-content-type
Dynamic: home-page
Dynamic: keywords
Dynamic: license
Dynamic: license-file
Dynamic: project-url
Dynamic: requires-dist
Dynamic: requires-python
Dynamic: summary
